funi.pypy38-pp73-aarch64-linux-gnu.so
lib/cmake/funi/funiConfigVersion.cmake
lib/cmake/funi/funiConfig.cmake
lib/cmake/funi/funiTargets.cmake
include/axis.hpp
include/lexi.hpp
include/pyfuni.hpp
funi-0.1.0.dist-info/WHEEL
funi-0.1.0.dist-info/RECORD
funi-0.1.0.dist-info/METADATA
funi-0.1.0.dist-info/licenses/LICENSE
