Metadata-Version: 2.1
Name: funi
Version: 0.1.0
Summary: Find unique float arrays.
Author-Email: Jaewook Lee <jaewooklee042@gmail.com>
License: MIT License
Classifier: Development Status :: 4 - Beta
Classifier: License :: OSI Approved :: MIT License
Classifier: Programming Language :: Python
Classifier: Natural Language :: English
Classifier: Topic :: Scientific/Engineering
Project-URL: Homepage, https://github.com/tataratat/funi
Requires-Python: >=3.7
Requires-Dist: numpy
